CHANGELOG.txt
LICENSE.txt
MANIFEST.in
README.txt
setup.py
fiplib/__init__.py
fiplib/data_cleaning.py
fiplib.egg-info/PKG-INFO
fiplib.egg-info/SOURCES.txt
fiplib.egg-info/dependency_links.txt
fiplib.egg-info/requires.txt
fiplib.egg-info/top_level.txt